{
  "report": {
    "id": 20260529,
    "report_date": "2026-05-29",
    "generated_at": "2026-05-29T12:04:40.7108443+08:00",
    "market_session": "premarket",
    "market_summary": "\u00202026-05-29 \u76d8\u524d\u7684\u4e3b\u7ebf\u662f Dell \u5728 2026-05-28 \u76d8\u540e\u7ee7\u7eed\u5f3a\u5316 AI \u670d\u52a1\u5668\u4e0e\u6570\u636e\u4e2d\u5fc3\u57fa\u5efa\u7684\u4e1a\u7ee9\u5151\u73b0\uff0c\u800c 2026-05-28 \u7684 PCE \u4e0e GDP \u7ec4\u5408\u6ca1\u6709\u6bd4\u9884\u671f\u66f4\u70ed\uff0c\u53e0\u52a0\u7f8e\u4f0a\u505c\u706b\u5ef6\u957f\u671f\u5f85\u538b\u4f4e\u6cb9\u4ef7\uff0c\u77ed\u7ebf\u6709\u5229\u4e8e\u98ce\u9669\u504f\u597d\uff1b\u4f46\u7f8e\u8054\u50a8\u5b98\u5458\u53e3\u5f84\u4ecd\u504f\u9e70\uff0c\u610f\u5473\u7740\u9ad8\u4f30\u503c\u6269\u5f20\u4ecd\u53d7\u7ea6\u675f\u3002",
    "overall_sentiment": "mixed",
    "main_theme": "\u20262026-05-29 \u76d8\u524d\u4e3b\u7ebf\uff1aAI \u57fa\u5efa\u7ee7\u7eed\u5151\u73b0\uff0c\u4f46\u5229\u7387\u4e0e\u5730\u7f18\u53d8\u91cf\u4ecd\u5728\u3002",
    "markdown_summary": "# Daily US Market Intelligence Report\n\u65e5\u671f\uff1a2026-05-29\n\u8986\u76d6\u8303\u56f4\uff1a2026-05-29 \u81f3 2026-06-05\n\u7f8e\u80a1\u72b6\u6001\uff1a\u76d8\u524d\n\n\u8be6\u89c1 Markdown \u6b63\u6587\uff1a2026-05/2026-05-29-Daily-US-Market-Intelligence-Report.md\n",
    "created_at": "2026-05-29T12:04:40.7108443+08:00",
    "updated_at": "2026-05-29T12:04:40.7108443+08:00"
  },
  "topSignals": [
    {
      "title": "Dell raised AI server expectations after 2026-05-28 results",
      "summary": "Dell reported fiscal 2027 first-quarter revenue of $43.8 billion, said AI server revenue reached $16.1 billion, and lifted its fiscal-year AI server revenue expectation to about $60 billion.",
      "why_it_matters": "This is evidence that AI demand is converting into revenue beyond upstream GPU suppliers and is spreading through servers, networking, and data center infrastructure.",
      "direction": "bullish",
      "affected_sectors": ["AI Infrastructure", "Servers", "Data Center Power"],
      "affected_tickers": ["DELL", "NVDA", "SMCI", "VRT", "ANET", "HPE"],
      "impact_horizon": "medium_term",
      "importance_score": 97,
      "source_urls": [
        {
          "title": "Dell FY2027 Q1 Results",
          "url": "https://www.marketscreener.com/news/dell-technologies-delivers-first-quarter-fiscal-2027-financial-results-ce7f5ddade8cf227"
        },
        {
          "title": "Reuters: Dell raises annual forecasts as AI data center buildout fuels demand",
          "url": "https://www.marketscreener.com/news/dell-raises-annual-forecasts-as-ai-data-center-buildout-fuels-demand-ce7f5ddade8cf024"
        }
      ]
    },
    {
      "title": "2026-05-28 PCE and GDP were not hotter than expected, but not dovish either",
      "summary": "BEA reported April 2026 PCE inflation at 3.8% year over year and core PCE at 3.3% year over year and 0.2% month over month, while first-quarter GDP second estimate was revised down to 1.6%.",
      "why_it_matters": "The macro mix is better than a renewed inflation scare, but still not weak enough to force a clear dovish turn from the Fed. That helps quality growth but does not fully support speculative multiple expansion.",
      "direction": "uncertain",
      "affected_sectors": ["Macro", "Rates", "Growth Tech"],
      "affected_tickers": ["QQQ", "SOXX", "TLT", "DXY"],
      "impact_horizon": "this_week",
      "importance_score": 95,
      "source_urls": [
        {
          "title": "BEA: Personal Income and Outlays, April 2026",
          "url": "https://www.bea.gov/news/2026/personal-income-and-outlays-april-2026"
        },
        {
          "title": "BEA: GDP Second Estimate and Corporate Profits, 1st Quarter 2026",
          "url": "https://www.bea.gov/news/2026/gdp-second-estimate-and-corporate-profits-1st-quarter-2026"
        },
        {
          "title": "Reuters: Inflation rises but isn't hotter than expected while GDP slips",
          "url": "https://whtc.com/2026/05/28/inflation-rises-but-isnt-hotter-than-expected-while-gdp-slips/"
        }
      ]
    },
    {
      "title": "US-Iran ceasefire extension headlines pressured oil lower, but the deal is not fully settled",
      "summary": "AP and Reuters reported a 60-day ceasefire extension framework and progress in nuclear talks, which reduced near-term expectations for a prolonged Hormuz disruption and weighed on oil prices.",
      "why_it_matters": "Lower oil can ease inflation pressure and support risk assets, but the market impact could reverse quickly if the framework breaks down or if approvals fail.",
      "direction": "uncertain",
      "affected_sectors": ["Energy", "Transportation", "Defense Tech", "Broad Market"],
      "affected_tickers": ["SPY", "QQQ", "XLE"],
      "impact_horizon": "this_week",
      "importance_score": 88,
      "source_urls": [
        {
          "title": "AP: Wall Street pushes to more records as profits keep piling up",
          "url": "https://apnews.com/article/559e1f1e5269976ea21bb551e916c941"
        },
        {
          "title": "AP: Iran negotiators agree to extend ceasefire",
          "url": "https://apnews.com/article/28efe5f84b72fe6cb382b14fb9350c31"
        },
        {
          "title": "Reuters: Oil falls slightly on reports of potential US-Iran ceasefire deal",
          "url": "https://www.marketscreener.com/news/oil-falls-slightly-on-reports-of-potential-us-iran-ceasefire-deal-ce7f5ddad08ef322"
        }
      ]
    },
    {
      "title": "Samsung began shipping HBM4E samples on 2026-05-29",
      "summary": "Samsung announced initial shipments of 12-layer HBM4E samples to global customers and described it as the first such product shipment in the industry.",
      "why_it_matters": "HBM remains a critical bottleneck in AI training and inference. Sample shipment is not the same as mass production, but it reinforces attention on memory, packaging, and bandwidth supply chains.",
      "direction": "bullish",
      "affected_sectors": ["Semiconductors", "HBM", "Advanced Packaging"],
      "affected_tickers": ["MU", "NVDA", "AMD", "TSM", "AVGO"],
      "impact_horizon": "medium_term",
      "importance_score": 82,
      "source_urls": [
        {
          "title": "Samsung HBM4E Samples",
          "url": "https://news.samsung.com/global/samsung-electronics-begins-shipment-of-industry-first-hbm4e-samples"
        },
        {
          "title": "Reuters: Samsung ships HBM4E samples",
          "url": "https://www.investing.com/news/stock-market-news/samsung-electronics-ships-hbm4e-chip-samples-to-global-customers-4715780"
        }
      ]
    },
    {
      "title": "Fed speakers remained hawkish across 2026-05-27 to 2026-05-28",
      "summary": "Cook said she was prepared to raise rates if inflation does not ease, Jefferson said he remained focused on inflation, and Williams said policy is in the right place given the outlook.",
      "why_it_matters": "Even after a softer-than-feared core PCE print, the Fed is not signaling an easy policy pivot. That keeps pressure on high-valuation software and duration-sensitive growth names.",
      "direction": "bearish",
      "affected_sectors": ["High Valuation Software", "Long Duration Growth"],
      "affected_tickers": ["ARKK", "QQQ"],
      "impact_horizon": "medium_term",
      "importance_score": 84,
      "source_urls": [
        {
          "title": "Reuters: Cook prepared to raise rates",
          "url": "https://whtc.com/2026/05/27/feds-cook-says-she-is-prepared-to-raise-rates-if-inflation-doesnt-ease/"
        },
        {
          "title": "Reuters: Jefferson focuses on inflation",
          "url": "https://whtc.com/2026/05/27/feds-jefferson-says-he-is-focusing-on-inflation-as-us-labour-market-very-resilient/"
        },
        {
          "title": "Reuters: Williams says policy is in the right place",
          "url": "https://whtc.com/2026/05/28/feds-williams-reiterates-rate-policy-is-in-right-place-given-outlook/"
        }
      ]
    }
  ],
  "events": [
    {
      "event_date": "2026-06-01",
      "event_name": "ISM Manufacturing PMI",
      "event_type": "macro",
      "importance": "high",
      "affected_assets": ["Industrials", "Materials", "Rates", "USD", "Cyclicals"],
      "watch_points": "Watch new orders, prices paid, and employment components for signs of better activity without renewed inflation heat.",
      "source_urls": [
        {
          "title": "ISM Report Calendar",
          "url": "https://www.ismworld.org/supply-management-news-and-reports/reports/rob-report-calendar/"
        }
      ]
    },
    {
      "event_date": "2026-06-01",
      "event_name": "Construction Spending",
      "event_type": "macro",
      "importance": "medium",
      "affected_assets": ["Power Equipment", "Engineering", "Data Center Infrastructure"],
      "watch_points": "Watch whether data center, grid, and industrial construction spending remains firm.",
      "source_urls": [
        {
          "title": "Census Construction Spending Schedule",
          "url": "https://www.census.gov/construction/c30/schedule.html"
        }
      ]
    },
    {
      "event_date": "2026-06-01",
      "event_name": "HPE fiscal 2026 second-quarter results",
      "event_type": "earnings",
      "importance": "high",
      "affected_assets": ["HPE", "ANET", "VRT", "AI Server Chain"],
      "watch_points": "Watch AI systems backlog, Juniper integration, and enterprise networking demand.",
      "source_urls": [
        {
          "title": "HPE Investor Events",
          "url": "https://investors.hpe.com/?jumpid=va_ycdgibe2fh%2Fhome%2Fdefault.aspx"
        }
      ]
    },
    {
      "event_date": "2026-06-02",
      "event_name": "JOLTS Job Openings",
      "event_type": "macro",
      "importance": "medium",
      "affected_assets": ["Rates", "Small Caps", "Consumer", "Regional Banks"],
      "watch_points": "Watch whether labor demand keeps cooling enough to offset inflation worries.",
      "source_urls": [
        {
          "title": "BLS JOLTS Release Calendar",
          "url": "https://www.bls.gov/schedule/news_release/jolts.htm"
        }
      ]
    },
    {
      "event_date": "2026-06-02",
      "event_name": "GitLab fiscal 2027 first-quarter results",
      "event_type": "earnings",
      "importance": "medium",
      "affected_assets": ["GTLB", "Developer Tools", "Enterprise AI Software"],
      "watch_points": "Watch paid AI coding adoption, seat expansion, and guidance quality.",
      "source_urls": [
        {
          "title": "GitLab results date",
          "url": "https://ir.gitlab.com/news/news-details/2026/GitLab-To-Announce-First-Quarter-Fiscal-2027-Financial-Results/default.aspx"
        }
      ]
    },
    {
      "event_date": "2026-06-03",
      "event_name": "Factory Orders and M3 report",
      "event_type": "macro",
      "importance": "medium",
      "affected_assets": ["Industrials", "Capex", "Manufacturing", "Automation"],
      "watch_points": "Watch new orders, inventories, and unfilled orders for confirmation of physical-economy demand.",
      "source_urls": [
        {
          "title": "Census M3 release",
          "url": "https://www.census.gov/manufacturing/m3/current/index.html"
        }
      ]
    },
    {
      "event_date": "2026-06-03",
      "event_name": "ISM Services PMI",
      "event_type": "macro",
      "importance": "high",
      "affected_assets": ["Software", "Consumer", "Rates", "USD"],
      "watch_points": "Watch prices paid and employment for evidence that services inflation is cooling or reaccelerating.",
      "source_urls": [
        {
          "title": "ISM Report Calendar",
          "url": "https://www.ismworld.org/supply-management-news-and-reports/reports/rob-report-calendar/"
        }
      ]
    },
    {
      "event_date": "2026-06-03",
      "event_name": "Federal Reserve Beige Book",
      "event_type": "macro",
      "importance": "medium",
      "affected_assets": ["Rates", "USD", "Banks", "Cyclicals"],
      "watch_points": "Watch qualitative changes in labor, wages, prices, consumer spending, and credit conditions.",
      "source_urls": [
        {
          "title": "Federal Reserve Beige Book",
          "url": "https://www.federalreserve.gov/monetarypolicy/publications/beige-book-default.htm"
        }
      ]
    },
    {
      "event_date": "2026-06-03",
      "event_name": "CrowdStrike fiscal 2027 first-quarter results",
      "event_type": "earnings",
      "importance": "high",
      "affected_assets": ["CRWD", "ZS", "PANW", "Cybersecurity"],
      "watch_points": "Watch whether cyber security can reassert growth quality after Zscaler's post-earnings drop.",
      "source_urls": [
        {
          "title": "CrowdStrike results date",
          "url": "https://ir.crowdstrike.com/news-releases/news-release-details/crowdstrike-announces-date-fiscal-first-quarter-2027-financial"
        }
      ]
    },
    {
      "event_date": "2026-06-03",
      "event_name": "Broadcom fiscal 2026 second-quarter results",
      "event_type": "earnings",
      "importance": "high",
      "affected_assets": ["AVGO", "MRVL", "NVDA", "AI Networking", "ASIC"],
      "watch_points": "Watch AI revenue, networking mix, customer concentration, and guidance into the next quarter.",
      "source_urls": [
        {
          "title": "Broadcom results date",
          "url": "https://investors.broadcom.com/news-releases/news-release-details/broadcom-inc-announce-second-quarter-fiscal-year-2026-financial"
        }
      ]
    },
    {
      "event_date": "2026-06-04",
      "event_name": "Productivity and Costs revised",
      "event_type": "macro",
      "importance": "medium",
      "affected_assets": ["Rates", "Wage Sensitive Sectors", "Software", "Services"],
      "watch_points": "Watch unit labor costs for renewed inflation pressure.",
      "source_urls": [
        {
          "title": "BLS Productivity schedule",
          "url": "https://www.bls.gov/schedule/news_release/prod2.htm"
        }
      ]
    },
    {
      "event_date": "2026-06-04",
      "event_name": "Weekly Initial Jobless Claims",
      "event_type": "macro",
      "importance": "medium",
      "affected_assets": ["Rates", "Consumer", "Small Caps"],
      "watch_points": "Watch whether labor-market cooling is continuing into the payroll report.",
      "source_urls": [
        {
          "title": "DOL weekly claims",
          "url": "https://oui.doleta.gov/unemploy/claims.asp"
        }
      ]
    },
    {
      "event_date": "2026-06-04",
      "event_name": "DocuSign fiscal 2027 first-quarter results",
      "event_type": "earnings",
      "importance": "medium",
      "affected_assets": ["DOCU", "Enterprise Software", "AI Applications"],
      "watch_points": "Watch whether AI-native identity and agreement tools improve ARR and margins.",
      "source_urls": [
        {
          "title": "DocuSign Q1 FY2027 Earnings Call",
          "url": "https://investor.docusign.com/news-and-events/events-and-presentations/event-details/2026/Docusign-Q1-Fiscal-2027-Earnings-Call-and-Webcast-2026-v-yTplEN4u/default.aspx"
        }
      ]
    },
    {
      "event_date": "2026-06-05",
      "event_name": "US Employment Situation for 2026-05",
      "event_type": "macro",
      "importance": "high",
      "affected_assets": ["All US Equities", "Rates", "USD", "Growth Tech"],
      "watch_points": "Watch payrolls, unemployment rate, and average hourly earnings for the next move in rate expectations.",
      "source_urls": [
        {
          "title": "BLS Employment Situation",
          "url": "https://www.bls.gov/ces/"
        }
      ]
    }
  ],
  "sectors": [
    {
      "sector_name": "AI Infrastructure / Servers / Data Center Power",
      "latest_catalysts": [
        "Dell raised its fiscal 2027 AI server revenue expectation to about $60 billion after 2026-05-28 results.",
        "HPE on 2026-06-01 and Broadcom on 2026-06-03 are the next checkpoints for whether AI demand is broadening into systems, networking, and supporting infrastructure."
      ],
      "beneficiary_tickers": ["DELL", "NVDA", "VRT", "ANET", "HPE", "SMCI"],
      "pressured_tickers": ["Speculative second-line AI hardware names without margin or delivery proof"],
      "watch_signals": ["AI server backlog", "delivery cadence", "gross margin", "hyperscaler capex", "power interconnect and cooling constraints"],
      "sentiment": "bullish",
      "source_urls": [
        {
          "title": "Dell FY2027 Q1 Results",
          "url": "https://www.marketscreener.com/news/dell-technologies-delivers-first-quarter-fiscal-2027-financial-results-ce7f5ddade8cf227"
        },
        {
          "title": "Reuters: Dell raises annual forecasts",
          "url": "https://www.marketscreener.com/news/dell-raises-annual-forecasts-as-ai-data-center-buildout-fuels-demand-ce7f5ddade8cf024"
        },
        {
          "title": "HPE Investor Events",
          "url": "https://investors.hpe.com/?jumpid=va_ycdgibe2fh%2Fhome%2Fdefault.aspx"
        },
        {
          "title": "Broadcom results date",
          "url": "https://investors.broadcom.com/news-releases/news-release-details/broadcom-inc-announce-second-quarter-fiscal-year-2026-financial"
        }
      ]
    },
    {
      "sector_name": "Semiconductors / HBM / Advanced Packaging",
      "latest_catalysts": [
        "Samsung began shipping HBM4E samples on 2026-05-29.",
        "Marvell continued to emphasize custom AI silicon, networking, and optics demand after 2026-05-27 results."
      ],
      "beneficiary_tickers": ["MU", "NVDA", "AMD", "TSM", "AVGO", "MRVL"],
      "pressured_tickers": ["Small-cap HBM and packaging theme names without proven production ramps"],
      "watch_signals": ["HBM4E qualification pace", "mass production timeline", "advanced packaging capacity", "customer design wins"],
      "sentiment": "bullish",
      "source_urls": [
        {
          "title": "Samsung HBM4E Samples",
          "url": "https://news.samsung.com/global/samsung-electronics-begins-shipment-of-industry-first-hbm4e-samples"
        },
        {
          "title": "Reuters: Samsung ships HBM4E samples",
          "url": "https://www.investing.com/news/stock-market-news/samsung-electronics-ships-hbm4e-chip-samples-to-global-customers-4715780"
        },
        {
          "title": "Marvell Q1 FY2027 Results",
          "url": "https://investor.marvell.com/news-events/press-releases/detail/1023/marvell-technology-inc-reports-first-quarter-of-fiscal-year-2027-financial-results"
        }
      ]
    },
    {
      "sector_name": "ASIC / Networking / Optical",
      "latest_catalysts": [
        "Marvell extended the AI expansion logic from GPUs into custom XPU, switching silicon, and optical interconnect.",
        "Broadcom's 2026-06-03 earnings are the next major validation point for AI networking and ASIC revenue concentration."
      ],
      "beneficiary_tickers": ["MRVL", "AVGO", "ANET", "LITE", "COHR", "CIEN"],
      "pressured_tickers": ["High-beta optical and switching names if Broadcom guidance does not exceed expectations"],
      "watch_signals": ["AI networking revenue mix", "800G and 1.6T shipments", "CPO and NPO commercialization", "hyperscaler custom ASIC cadence"],
      "sentiment": "bullish",
      "source_urls": [
        {
          "title": "Marvell Q1 FY2027 Results",
          "url": "https://investor.marvell.com/news-events/press-releases/detail/1023/marvell-technology-inc-reports-first-quarter-of-fiscal-year-2027-financial-results"
        },
        {
          "title": "Marvell NVLink Fusion / Custom AI XPU",
          "url": "https://investor.marvell.com/news/news-details/2026/Marvell-Extends-Custom-AI-XPU-Strategy-with-NVLink-Fusion/default.aspx"
        },
        {
          "title": "Broadcom results date",
          "url": "https://investors.broadcom.com/news-releases/news-release-details/broadcom-inc-announce-second-quarter-fiscal-year-2026-financial"
        }
      ]
    },
    {
      "sector_name": "Cloud Software / Enterprise AI / Cybersecurity",
      "latest_catalysts": [
        "Snowflake lifted full-year product revenue guidance after 2026-05-27 results.",
        "Salesforce beat on results but its quarterly revenue outlook missed expectations, while CrowdStrike and DocuSign will test whether enterprise AI software demand can convert into durable guidance."
      ],
      "beneficiary_tickers": ["SNOW", "MSFT", "AMZN", "DOCU"],
      "pressured_tickers": ["CRM", "ZS"],
      "watch_signals": ["RPO", "net revenue retention", "AI feature monetization", "free cash flow margin"],
      "sentiment": "mixed",
      "source_urls": [
        {
          "title": "Snowflake Q1 FY2027 Results",
          "url": "https://www.sec.gov/Archives/edgar/data/1640147/000164014726000027/fy2027q1earnings.htm"
        },
        {
          "title": "Salesforce FY2027 Q1 Results",
          "url": "https://investor.salesforce.com/news/news-details/2026/Salesforce-Delivers-Record-First-Quarter-Fiscal-2027-Results/default.aspx"
        },
        {
          "title": "Reuters: Salesforce sees quarterly revenue below estimates",
          "url": "https://whtc.com/2026/05/27/salesforce-sees-quarterly-revenue-below-estimates-amid-ai-disruption-fears/"
        },
        {
          "title": "CrowdStrike results date",
          "url": "https://ir.crowdstrike.com/news-releases/news-release-details/crowdstrike-announces-date-fiscal-first-quarter-2027-financial"
        },
        {
          "title": "DocuSign earnings call",
          "url": "https://investor.docusign.com/news-and-events/events-and-presentations/event-details/2026/Docusign-Q1-Fiscal-2027-Earnings-Call-and-Webcast-2026-v-yTplEN4u/default.aspx"
        }
      ]
    }
  ],
  "macro": {
    "treasury_yields": "2026-05-29 \u76d8\u524d\u9700\u7ee7\u7eed\u89c2\u5bdf 10Y \u7f8e\u503a\u6536\u76ca\u7387\u662f\u5426\u56e0 2026-05-28 \u7684 PCE/GDP \u7ec4\u5408\u800c\u7ef4\u6301\u5728\u4e0d\u538b\u5236\u6210\u957f\u80a1\u7684\u533a\u95f4\u3002",
    "dollar_index": "Reuters \u62a5\u9053\u79f0 2026-05-29 \u4e9a\u6d32\u65f6\u6bb5\u7f8e\u5143\u6709\u671b\u5468\u7ebf\u8d70\u5f31\uff0c\u7f13\u89e3\u4e86\u79d1\u6280\u4f30\u503c\u538b\u529b\uff0c\u4f46\u8fd9\u4ecd\u9700\u8981\u540e\u7eed\u5b8f\u89c2\u6570\u636e\u786e\u8ba4\u3002",
    "crude_oil": "Oil softened on ceasefire-extension headlines, which is near-term positive for inflation expectations but remains contingent on whether the diplomatic framework holds.",
    "gold": "\u9ec4\u91d1\u4e0d\u662f\u672c\u65e5\u62a5\u544a\u7684\u4e3b\u53d8\u91cf\uff0c\u4f46\u82e5\u5730\u7f18\u6216\u5229\u7387\u9884\u671f\u53cd\u590d\uff0c\u4ecd\u53ef\u4f5c\u4e3a\u98ce\u9669\u5bf9\u51b2\u89c2\u5bdf\u9879\u3002",
    "vix": "Risk appetite stayed constructive into 2026-05-29 premarket, but VIX direction should still be checked against rates and payroll-related expectations.",
    "macro_data": "The main macro mix is slowing growth without a fresh inflation shock. That is supportive for large-cap AI and quality growth in the short run, but not enough to remove the Fed from the equation.",
    "growth_tech_smallcap_impact": "\u5bf9\u5927\u578b AI \u4e0e\u73b0\u91d1\u6d41\u8f83\u5f3a\u7684\u79d1\u6280\u9f99\u5934\u504f\u4e2d\u6027\u7565\u5229\u597d\uff1b\u5bf9\u7eaf\u9898\u6750\u578b\u5c0f\u76d8\u6210\u957f\u80a1\u4ecd\u662f\u201c\u4e0d\u591f\u5bbd\u677e\u201d\u7684\u73af\u5883\u3002",
    "source_urls": [
      {
        "title": "BEA: Personal Income and Outlays, April 2026",
        "url": "https://www.bea.gov/news/2026/personal-income-and-outlays-april-2026"
      },
      {
        "title": "BEA: GDP Second Estimate and Corporate Profits, 1st Quarter 2026",
        "url": "https://www.bea.gov/news/2026/gdp-second-estimate-and-corporate-profits-1st-quarter-2026"
      },
      {
        "title": "Reuters: Inflation rises but isn't hotter than expected while GDP slips",
        "url": "https://whtc.com/2026/05/28/inflation-rises-but-isnt-hotter-than-expected-while-gdp-slips/"
      },
      {
        "title": "Reuters: Dollar heads for weekly loss on ceasefire reports",
        "url": "https://www.marketscreener.com/news/dollar-heads-for-weekly-loss-on-reports-of-us-iran-ceasefire-deal-ce7f5ddad08ef22d"
      },
      {
        "title": "Reuters: Oil falls slightly on reports of potential US-Iran ceasefire deal",
        "url": "https://www.marketscreener.com/news/oil-falls-slightly-on-reports-of-potential-us-iran-ceasefire-deal-ce7f5ddad08ef322"
      },
      {
        "title": "AP market recap",
        "url": "https://apnews.com/article/69f6b6c8b2bf904c69087af415812d4c"
      },
      {
        "title": "Reuters: Williams says policy is in the right place",
        "url": "https://whtc.com/2026/05/28/feds-williams-reiterates-rate-policy-is-in-right-place-given-outlook/"
      }
    ]
  },
  "decliners": [
    {
      "ticker": "ZCMD",
      "company_name": "Zhongchao Inc.",
      "previous_day_change_percent": -65.14,
      "volume_note": "Micro-cap move with limited explanatory disclosure identified in public sources reviewed for 2026-05-28.",
      "reason": "No reliable same-day company filing or press release was found during this run. The move appears more likely related to liquidity, trading pressure, or micro-cap structure than to a clearly verified fundamental catalyst.",
      "reason_type": "unknown",
      "catalysts": ["Micro-cap price action", "Potential liquidity or financing pressure", "Needs filing confirmation"],
      "watch_points": "Watch for any 8-K, financing, delisting, or operating update that can explain the move.",
      "source_urls": [
        {
          "title": "StockAnalysis losers 2026-05-28",
          "url": "https://stockanalysis.com/markets/losers/"
        }
      ]
    },
    {
      "ticker": "SUGP",
      "company_name": "SU Group Holdings Limited",
      "previous_day_change_percent": -44.09,
      "volume_note": "Another small-cap move with limited reliable same-day catalyst disclosure.",
      "reason": "No sufficiently reliable first-hand filing or company announcement was found during this run to explain the one-day decline. Current judgment remains uncertain and likely trading-driven.",
      "reason_type": "unknown",
      "catalysts": ["Micro-cap volatility", "Possible financing or compliance overhang", "Needs disclosure confirmation"],
      "watch_points": "Watch for capital raise, compliance, or operations-related filings.",
      "source_urls": [
        {
          "title": "StockAnalysis losers 2026-05-28",
          "url": "https://stockanalysis.com/markets/losers/"
        }
      ]
    },
    {
      "ticker": "PLAB",
      "company_name": "Photronics, Inc.",
      "previous_day_change_percent": -36.42,
      "volume_note": "Larger and more fundamentally relevant decline than the micro-cap movers above.",
      "reason": "Photronics reported fiscal second-quarter 2026 results on 2026-05-28, and the market reaction pointed to weaker revenue, earnings, and/or outlook expectations versus what investors had priced in.",
      "reason_type": "company_specific",
      "catalysts": ["Quarterly earnings release", "Expectation reset", "Semiconductor photomask demand concerns"],
      "watch_points": "Watch next-quarter orders, integrated circuit demand recovery, and management commentary on customer spending.",
      "source_urls": [
        {
          "title": "StockAnalysis losers 2026-05-28",
          "url": "https://stockanalysis.com/markets/losers/"
        },
        {
          "title": "Photronics fiscal Q2 2026 results release PDF",
          "url": "https://photronicsinc.gcs-web.com/node/19596/pdf"
        },
        {
          "title": "Why Photronics Stock Is Plummeting Today",
          "url": "https://www.fool.com/investing/2026/05/28/why-photronics-stock-is-plummeting-today/"
        }
      ]
    },
    {
      "ticker": "ADTX",
      "company_name": "Aditxt, Inc.",
      "previous_day_change_percent": -19.96,
      "volume_note": "Low-priced micro-cap under continuing listing and financing stress.",
      "reason": "Aditxt disclosed Nasdaq delisting determination risk on 2026-05-06 and reverse split-related filings on 2026-05-14. The 2026-05-28 decline looks consistent with an ongoing repricing of listing and capital-market risk.",
      "reason_type": "company_specific",
      "catalysts": ["Nasdaq delisting risk", "Reverse split", "Financing overhang"],
      "watch_points": "Watch appeal status, listing venue outcome, and further capital raises.",
      "source_urls": [
        {
          "title": "StockAnalysis losers 2026-05-28",
          "url": "https://stockanalysis.com/markets/losers/"
        },
        {
          "title": "Aditxt Nasdaq delisting determination 8-K",
          "url": "https://www.sec.gov/Archives/edgar/data/1726711/000121390026053904/ea0289662-8k_aditxt.htm"
        },
        {
          "title": "Aditxt reverse split 8-K",
          "url": "https://www.sec.gov/Archives/edgar/data/1726711/000121390026057811/ea0290707-8k_aditxt.htm"
        }
      ]
    }
  ],
  "watchlist": [
    {
      "symbol_or_sector": "DELL",
      "reason_to_watch": "Dell delivered one of the clearest new proof points that AI server demand is converting into real revenue and guidance.",
      "key_trigger": "Watch whether 2026-05-29 price action holds after the post-earnings gap and whether analysts keep revising full-year expectations higher.",
      "risk_points": "If the opening move is overextended or margin details disappoint, the market could treat the print as a sell-the-news event.",
      "priority": "high",
      "source_urls": [
        {
          "title": "Dell FY2027 Q1 Results",
          "url": "https://www.marketscreener.com/news/dell-technologies-delivers-first-quarter-fiscal-2027-financial-results-ce7f5ddade8cf227"
        },
        {
          "title": "Reuters Dell recap",
          "url": "https://www.marketscreener.com/news/dell-raises-annual-forecasts-as-ai-data-center-buildout-fuels-demand-ce7f5ddade8cf024"
        }
      ]
    },
    {
      "symbol_or_sector": "AVGO / MRVL / AI Networking",
      "reason_to_watch": "Broadcom earnings on 2026-06-03 are the next major validation point for the AI networking and custom silicon trade after Marvell and Dell.",
      "key_trigger": "Watch whether expectations keep building into the report and whether optical and switching names continue to move in sympathy.",
      "risk_points": "If Broadcom guidance merely meets expectations, the highest-beta networking and optical names could retrace quickly.",
      "priority": "high",
      "source_urls": [
        {
          "title": "Marvell Q1 FY2027 Results",
          "url": "https://investor.marvell.com/news-events/press-releases/detail/1023/marvell-technology-inc-reports-first-quarter-of-fiscal-year-2027-financial-results"
        },
        {
          "title": "Broadcom results date",
          "url": "https://investors.broadcom.com/news-releases/news-release-details/broadcom-inc-announce-second-quarter-fiscal-year-2026-financial"
        }
      ]
    },
    {
      "symbol_or_sector": "HPE / VRT / Data Center Power",
      "reason_to_watch": "Dell already strengthened the downstream AI infrastructure story, so HPE and data center support-chain names become the next check for breadth and delivery quality.",
      "key_trigger": "Watch HPE results on 2026-06-01, especially AI systems backlog, delivery timing, and commentary on enterprise and networking demand.",
      "risk_points": "Strong orders with weak margins would revive doubts about how much value downstream OEMs and infrastructure suppliers actually retain.",
      "priority": "high",
      "source_urls": [
        {
          "title": "HPE Investor Events",
          "url": "https://investors.hpe.com/?jumpid=va_ycdgibe2fh%2Fhome%2Fdefault.aspx"
        },
        {
          "title": "Reuters Dell recap",
          "url": "https://www.marketscreener.com/news/dell-raises-annual-forecasts-as-ai-data-center-buildout-fuels-demand-ce7f5ddade8cf024"
        }
      ]
    },
    {
      "symbol_or_sector": "SNOW / Enterprise AI Software",
      "reason_to_watch": "Snowflake has already shown a positive enterprise AI monetization response, but the software group remains selective rather than broadly risk-on.",
      "key_trigger": "Watch whether Snowflake can hold leadership while rates remain firm and whether peers begin to trade on conversion metrics rather than only product stories.",
      "risk_points": "If yields rise again, high-multiple software could underperform even with good company-specific AI narratives.",
      "priority": "high",
      "source_urls": [
        {
          "title": "Snowflake Q1 FY2027 Results",
          "url": "https://www.sec.gov/Archives/edgar/data/1640147/000164014726000027/fy2027q1earnings.htm"
        }
      ]
    },
    {
      "symbol_or_sector": "CRWD / Cybersecurity",
      "reason_to_watch": "Zscaler's sharp reaction raised the standard for security software guidance, making CrowdStrike a critical group-level read on 2026-06-03.",
      "key_trigger": "Watch net new ARR, margins, and full-year guidance quality in relation to current expectations.",
      "risk_points": "If guidance is only in line, the market may extend the post-ZS de-rating across software security names.",
      "priority": "high",
      "source_urls": [
        {
          "title": "CrowdStrike results date",
          "url": "https://ir.crowdstrike.com/news-releases/news-release-details/crowdstrike-announces-date-fiscal-first-quarter-2027-financial"
        },
        {
          "title": "Zscaler post-earnings reaction",
          "url": "https://www.investing.com/news/earnings/zscaler-shares-tumble-as-lower-free-cash-flow-outlook-overshadows-upbeat-q3-result-4710786"
        }
      ]
    },
    {
      "symbol_or_sector": "10Y Treasury / USD / Payroll chain",
      "reason_to_watch": "The 2026-06-01 to 2026-06-05 macro sequence remains the main cross-asset governor for how far AI and growth valuations can extend.",
      "key_trigger": "Watch ISM on 2026-06-01 and 2026-06-03, JOLTS on 2026-06-02, weekly claims on 2026-06-04, and payrolls on 2026-06-05.",
      "risk_points": "Any renewed wage or inflation pressure could reverse the current support from the softer-than-feared 2026-05-28 PCE print.",
      "priority": "high",
      "source_urls": [
        {
          "title": "BLS Employment Situation",
          "url": "https://www.bls.gov/ces/"
        },
        {
          "title": "BLS JOLTS schedule",
          "url": "https://www.bls.gov/schedule/news_release/jolts.htm"
        },
        {
          "title": "ISM calendar",
          "url": "https://www.ismworld.org/supply-management-news-and-reports/reports/rob-report-calendar/"
        }
      ]
    }
  ],
  "narratives": [],
  "sources": [
    {
      "title": "Dell FY2027 Q1 Results",
      "url": "https://www.marketscreener.com/news/dell-technologies-delivers-first-quarter-fiscal-2027-financial-results-ce7f5ddade8cf227",
      "publisher": "MarketScreener",
      "related_section": "topSignals"
    },
    {
      "title": "Reuters: Dell raises annual forecasts as AI data center buildout fuels demand",
      "url": "https://www.marketscreener.com/news/dell-raises-annual-forecasts-as-ai-data-center-buildout-fuels-demand-ce7f5ddade8cf024",
      "publisher": "Reuters via MarketScreener",
      "related_section": "topSignals"
    },
    {
      "title": "BEA: Personal Income and Outlays, April 2026",
      "url": "https://www.bea.gov/news/2026/personal-income-and-outlays-april-2026",
      "publisher": "BEA",
      "related_section": "macro"
    },
    {
      "title": "BEA: GDP Second Estimate and Corporate Profits, 1st Quarter 2026",
      "url": "https://www.bea.gov/news/2026/gdp-second-estimate-and-corporate-profits-1st-quarter-2026",
      "publisher": "BEA",
      "related_section": "macro"
    },
    {
      "title": "Reuters: Inflation rises but isn't hotter than expected while GDP slips",
      "url": "https://whtc.com/2026/05/28/inflation-rises-but-isnt-hotter-than-expected-while-gdp-slips/",
      "publisher": "Reuters via WHTC",
      "related_section": "macro"
    },
    {
      "title": "AP: Wall Street pushes to more records as profits keep piling up",
      "url": "https://apnews.com/article/559e1f1e5269976ea21bb551e916c941",
      "publisher": "AP",
      "related_section": "topSignals"
    },
    {
      "title": "AP: Iran negotiators agree to extend ceasefire",
      "url": "https://apnews.com/article/28efe5f84b72fe6cb382b14fb9350c31",
      "publisher": "AP",
      "related_section": "topSignals"
    },
    {
      "title": "AP market recap",
      "url": "https://apnews.com/article/69f6b6c8b2bf904c69087af415812d4c",
      "publisher": "AP",
      "related_section": "macro"
    },
    {
      "title": "Reuters: Oil falls slightly on reports of potential US-Iran ceasefire deal",
      "url": "https://www.marketscreener.com/news/oil-falls-slightly-on-reports-of-potential-us-iran-ceasefire-deal-ce7f5ddad08ef322",
      "publisher": "Reuters via MarketScreener",
      "related_section": "macro"
    },
    {
      "title": "Reuters: Dollar heads for weekly loss on ceasefire reports",
      "url": "https://www.marketscreener.com/news/dollar-heads-for-weekly-loss-on-reports-of-us-iran-ceasefire-deal-ce7f5ddad08ef22d",
      "publisher": "Reuters via MarketScreener",
      "related_section": "macro"
    },
    {
      "title": "Samsung HBM4E Samples",
      "url": "https://news.samsung.com/global/samsung-electronics-begins-shipment-of-industry-first-hbm4e-samples",
      "publisher": "Samsung",
      "related_section": "sectors"
    },
    {
      "title": "Reuters: Samsung ships HBM4E samples",
      "url": "https://www.investing.com/news/stock-market-news/samsung-electronics-ships-hbm4e-chip-samples-to-global-customers-4715780",
      "publisher": "Reuters via Investing.com",
      "related_section": "sectors"
    },
    {
      "title": "Reuters: Cook prepared to raise rates",
      "url": "https://whtc.com/2026/05/27/feds-cook-says-she-is-prepared-to-raise-rates-if-inflation-doesnt-ease/",
      "publisher": "Reuters via WHTC",
      "related_section": "topSignals"
    },
    {
      "title": "Reuters: Jefferson focuses on inflation",
      "url": "https://whtc.com/2026/05/27/feds-jefferson-says-he-is-focusing-on-inflation-as-us-labour-market-very-resilient/",
      "publisher": "Reuters via WHTC",
      "related_section": "topSignals"
    },
    {
      "title": "Reuters: Williams says policy is in the right place",
      "url": "https://whtc.com/2026/05/28/feds-williams-reiterates-rate-policy-is-in-right-place-given-outlook/",
      "publisher": "Reuters via WHTC",
      "related_section": "topSignals"
    },
    {
      "title": "HPE Investor Events",
      "url": "https://investors.hpe.com/?jumpid=va_ycdgibe2fh%2Fhome%2Fdefault.aspx",
      "publisher": "HPE IR",
      "related_section": "events"
    },
    {
      "title": "GitLab results date",
      "url": "https://ir.gitlab.com/news/news-details/2026/GitLab-To-Announce-First-Quarter-Fiscal-2027-Financial-Results/default.aspx",
      "publisher": "GitLab IR",
      "related_section": "events"
    },
    {
      "title": "CrowdStrike results date",
      "url": "https://ir.crowdstrike.com/news-releases/news-release-details/crowdstrike-announces-date-fiscal-first-quarter-2027-financial",
      "publisher": "CrowdStrike IR",
      "related_section": "events"
    },
    {
      "title": "Broadcom results date",
      "url": "https://investors.broadcom.com/news-releases/news-release-details/broadcom-inc-announce-second-quarter-fiscal-year-2026-financial",
      "publisher": "Broadcom IR",
      "related_section": "events"
    },
    {
      "title": "Snowflake Q1 FY2027 Results",
      "url": "https://www.sec.gov/Archives/edgar/data/1640147/000164014726000027/fy2027q1earnings.htm",
      "publisher": "SEC filing",
      "related_section": "sectors"
    },
    {
      "title": "Salesforce FY2027 Q1 Results",
      "url": "https://investor.salesforce.com/news/news-details/2026/Salesforce-Delivers-Record-First-Quarter-Fiscal-2027-Results/default.aspx",
      "publisher": "Salesforce IR",
      "related_section": "sectors"
    },
    {
      "title": "Reuters: Salesforce sees quarterly revenue below estimates",
      "url": "https://whtc.com/2026/05/27/salesforce-sees-quarterly-revenue-below-estimates-amid-ai-disruption-fears/",
      "publisher": "Reuters via WHTC",
      "related_section": "sectors"
    },
    {
      "title": "Photronics fiscal Q2 2026 results release PDF",
      "url": "https://photronicsinc.gcs-web.com/node/19596/pdf",
      "publisher": "Photronics IR",
      "related_section": "decliners"
    },
    {
      "title": "Why Photronics Stock Is Plummeting Today",
      "url": "https://www.fool.com/investing/2026/05/28/why-photronics-stock-is-plummeting-today/",
      "publisher": "The Motley Fool",
      "related_section": "decliners"
    },
    {
      "title": "Aditxt Nasdaq delisting determination 8-K",
      "url": "https://www.sec.gov/Archives/edgar/data/1726711/000121390026053904/ea0289662-8k_aditxt.htm",
      "publisher": "SEC filing",
      "related_section": "decliners"
    },
    {
      "title": "Aditxt reverse split 8-K",
      "url": "https://www.sec.gov/Archives/edgar/data/1726711/000121390026057811/ea0290707-8k_aditxt.htm",
      "publisher": "SEC filing",
      "related_section": "decliners"
    },
    {
      "title": "Zscaler post-earnings reaction",
      "url": "https://www.investing.com/news/earnings/zscaler-shares-tumble-as-lower-free-cash-flow-outlook-overshadows-upbeat-q3-result-4710786",
      "publisher": "Investing.com",
      "related_section": "watchlist"
    },
    {
      "title": "StockAnalysis losers 2026-05-28",
      "url": "https://stockanalysis.com/markets/losers/",
      "publisher": "StockAnalysis",
      "related_section": "decliners"
    }
  ]
}
